uvdat_flood_sim/__init__.py
uvdat_flood_sim/__main__.py
uvdat_flood_sim/animate_results.py
uvdat_flood_sim/constants.py
uvdat_flood_sim/downscaling_prediction.py
uvdat_flood_sim/hydrodynamic_prediction.py
uvdat_flood_sim/hydrological_prediction.py
uvdat_flood_sim/py.typed
uvdat_flood_sim/run.py
uvdat_flood_sim/save_results.py
uvdat_flood_sim/data/boston_cesm2-001_2031_2050.npy
uvdat_flood_sim/data/boston_cesm2-001_2041_2060.npy
uvdat_flood_sim/data/boston_cesm2-002_2031_2050.npy
uvdat_flood_sim/data/boston_cesm2-002_2041_2060.npy
uvdat_flood_sim/data/boston_cesm2-003_2031_2050.npy
uvdat_flood_sim/data/boston_cesm2-003_2041_2060.npy
uvdat_flood_sim/data/boston_hand.tif
uvdat_flood_sim/data/downscaling_model.pkl
uvdat_flood_sim/data/flood_param_percentiles.json
uvdat_flood_sim/data/hydrological_model.npy
uvdat_flood_sim/data/rating_curve.csv
uvdat_flood_sim-1.0.2.dist-info/METADATA
uvdat_flood_sim-1.0.2.dist-info/WHEEL
uvdat_flood_sim-1.0.2.dist-info/licenses/LICENSE
uvdat_flood_sim-1.0.2.dist-info/RECORD
