Metadata-Version: 2.4
Name: uvdat-flood-sim
Version: 1.0.2
Summary: An end-to-end dynamic flood simulation.
Project-URL: Repository, https://github.com/OpenGeoscience/uvdat-flood-sim
Project-URL: Bug Reports, https://github.com/OpenGeoscience/uvdat-flood-sim/issues
Maintainer-email: "Kitware, Inc." <kitware@kitware.com>, August Posch <augustposch@augustposch.us>
License-Expression: MIT
License-File: LICENSE
Requires-Python: >=3.10
Requires-Dist: click
Requires-Dist: matplotlib
Requires-Dist: numpy<2
Requires-Dist: pandas
Requires-Dist: pyproj
Requires-Dist: rasterio
Requires-Dist: requests
Requires-Dist: scikit-learn==1.3.0
Requires-Dist: scipy
Provides-Extra: large-image-writer
Requires-Dist: large-image[zarr]; extra == 'large-image-writer'
Requires-Dist: tifftools; extra == 'large-image-writer'
